codewarden/__init__.py
codewarden/airlock.py
codewarden/client.py
codewarden/evidence/__init__.py
codewarden/evidence/access.py
codewarden/evidence/collector.py
codewarden/evidence/deploy.py
codewarden/exceptions.py
codewarden/middleware/__init__.py
codewarden/middleware/base.py
codewarden/middleware/django.py
codewarden/middleware/fastapi.py
codewarden/middleware/flask.py
codewarden/scanners/__init__.py
codewarden/scanners/base.py
codewarden/scanners/code.py
codewarden/scanners/dependency.py
codewarden/scanners/secret.py
codewarden/transport.py
codewarden/types.py
codewarden/watchdog.py
codewarden-0.1.2.dist-info/METADATA
codewarden-0.1.2.dist-info/WHEEL
codewarden-0.1.2.dist-info/RECORD
