Metadata-Version: 2.4
Name: codewarden
Version: 0.1.2
Summary: CodeWarden Python SDK - Security and observability for your applications
License: MIT
Keywords: security,monitoring,observability,error-tracking,pii
Author: CodeWarden Team
Author-email: team@codewarden.io
Requires-Python: >=3.9,<4.0
Classifier: Development Status :: 4 - Beta
Classifier: Intended Audience :: Developers
Classifier: License :: OSI Approved :: MIT License
Classifier: Programming Language :: Python :: 3
Classifier: Programming Language :: Python :: 3.9
Classifier: Programming Language :: Python :: 3.10
Classifier: Programming Language :: Python :: 3.11
Classifier: Programming Language :: Python :: 3.12
Classifier: Programming Language :: Python :: 3.13
Classifier: Programming Language :: Python :: 3.14
Classifier: Typing :: Typed
Requires-Dist: httpx (>=0.28.0,<0.29.0)
Requires-Dist: pydantic (>=2.10.0,<3.0.0)
Project-URL: Documentation, https://codewarden.io/docs
Project-URL: Homepage, https://codewarden.io
Project-URL: Repository, https://github.com/simanam/codewarden
